jaraco/versioning.py
jaraco.versioning-1.1.0.dist-info/LICENSE
jaraco.versioning-1.1.0.dist-info/METADATA
jaraco.versioning-1.1.0.dist-info/WHEEL
jaraco.versioning-1.1.0.dist-info/top_level.txt
jaraco.versioning-1.1.0.dist-info/RECORD
